pandaprot/__init__.py
pandaprot/core.py
pandaprot/main.py
pandaprot/interactions/__init__.py
pandaprot/interactions/amide_amide.py
pandaprot/interactions/amide_aromatic.py
pandaprot/interactions/cation_pi.py
pandaprot/interactions/ch_pi.py
pandaprot/interactions/disulfide.py
pandaprot/interactions/halogen_bonds.py
pandaprot/interactions/hydrogen_bonds.py
pandaprot/interactions/hydrophobic.py
pandaprot/interactions/ionic.py
pandaprot/interactions/metal_coordination.py
pandaprot/interactions/pi_interactions.py
pandaprot/interactions/salt_bridges.py
pandaprot/interactions/sulfur_aromatic.py
pandaprot/interactions/utils.py
pandaprot/interactions/van_der_waals.py
pandaprot/interactions/water_mediated.py
pandaprot/reports/__init__.py
pandaprot/reports/generator.py
pandaprot/visualization/__init__.py
pandaprot/visualization/network.py
pandaprot/visualization/plot3d.py
pandaprot/visualization/plot_3d_enhanced.py
pandaprot-1.1.0.dist-info/licenses/LICENSE
pandaprot-1.1.0.dist-info/METADATA
pandaprot-1.1.0.dist-info/WHEEL
pandaprot-1.1.0.dist-info/entry_points.txt
pandaprot-1.1.0.dist-info/top_level.txt
pandaprot-1.1.0.dist-info/RECORD
