Metadata-Version: 2.4
Name: pandaprot
Version: 1.1.0
Summary: A tool for mapping protein-protein, protein-nucleic acid, and antigen-antibody interactions
Author-email: "Dr. Pritam Kumar Panda" <pritam@stanford.edu>
License: MIT
Project-URL: Homepage, https://github.com/pritampanda15/PandaProt
Project-URL: Bug Tracker, https://github.com/pritampanda15/PandaProt/issues
Keywords: bioinformatics,protein interactions,nucleic acids,antibodies
Classifier: Programming Language :: Python :: 3
Classifier: Operating System :: OS Independent
Classifier: Topic :: Scientific/Engineering :: Bio-Informatics
Classifier: Topic :: Scientific/Engineering :: Chemistry
Requires-Python: >=3.7
License-File: LICENSE
Requires-Dist: biopython>=1.79
Requires-Dist: numpy>=1.20.0
Requires-Dist: pandas>=1.3.0
Requires-Dist: matplotlib>=3.4.0
Requires-Dist: py3Dmol>=0.9.0
Requires-Dist: networkx>=2.6.0
Requires-Dist: scikit-learn>=0.24.0
Requires-Dist: scipy>=1.7.0
Dynamic: license-file
